bim2rdf/cache/__init__.py
bim2rdf/cache/cache.py
bim2rdf/cli/__init__.py
bim2rdf/cli/main.py
bim2rdf/cli/patch.py
bim2rdf/core/__init__.py
bim2rdf/core/config.py
bim2rdf/core/engine.py
bim2rdf/core/queries.py
bim2rdf/core/rdf.py
bim2rdf/core/utils/__init__.py
bim2rdf/core/utils/substitution.py
bim2rdf/mapping/__init__.py
bim2rdf/mapping/construct/__init__.py
bim2rdf/mapping/construct/queries.py
bim2rdf/mapping/construct/readme.md
bim2rdf/mapping/construct/architecture/lighting devices/lumocc.mapping.rq
bim2rdf/mapping/construct/architecture/lighting devices/sensor-lightingspace.mapping.rq
bim2rdf/mapping/construct/architecture/lighting devices/sensor-room.mapping.rq
bim2rdf/mapping/construct/architecture/rooms and lighting fixtures/connection-lightingdomainspace.mapping.rq
bim2rdf/mapping/construct/architecture/rooms and lighting fixtures/floor-room.mapping.rq
bim2rdf/mapping/construct/architecture/rooms and lighting fixtures/floor.mapping.rq
bim2rdf/mapping/construct/architecture/rooms and lighting fixtures/lighting-hvac-space-room.mapping.rq
bim2rdf/mapping/construct/architecture/rooms and lighting fixtures/lightingfixture-room.mapping.rq
bim2rdf/mapping/construct/architecture/rooms and lighting fixtures/lightingspace.mapping.rq
bim2rdf/mapping/construct/architecture/rooms and lighting fixtures/lightingzone-lightingspace.mapping.rq
bim2rdf/mapping/construct/architecture/rooms and lighting fixtures/lightingzone.mapping.rq
bim2rdf/mapping/construct/architecture/rooms and lighting fixtures/luminaire-to-space.data.rq
bim2rdf/mapping/construct/architecture/rooms and lighting fixtures/luminaire.mapping.rq
bim2rdf/mapping/construct/architecture/rooms and lighting fixtures/room.mapping.rq
bim2rdf/mapping/construct/electrical/electrical connections/voltagedrop-params.mapping.rq
bim2rdf/mapping/construct/electrical/electrical connections/wirelength-params.mapping.rq
bim2rdf/mapping/construct/electrical/main panels/mainpanel.mapping.rq
bim2rdf/ontologies/__init__.py
bim2rdf-2025.12.1861.dist-info/METADATA
bim2rdf-2025.12.1861.dist-info/WHEEL
bim2rdf-2025.12.1861.dist-info/entry_points.txt
bim2rdf-2025.12.1861.dist-info/licenses/LICENSE.md
bim2rdf-2025.12.1861.dist-info/RECORD
