Metadata-Version: 2.4
Name: bim2rdf
Version: 2025.12.1861
Summary: Convert BIM data to RDF models
Author-email: Majid alDosari <majid.aldosari@pnnl.gov>, Trisha Gupta <trisha.gupta@pnnl.gov>
License-File: LICENSE.md
Requires-Python: >=3.13
Requires-Dist: boltons
Requires-Dist: dynaconf
Requires-Dist: gql[requests]
Requires-Dist: json2rdf
Requires-Dist: json2rdf>=67
Requires-Dist: ontoenv==0.4.0
Requires-Dist: pyoxigraph
Requires-Dist: pytqshacl[java]
Requires-Dist: rdf-engine
Requires-Dist: rdflib
Provides-Extra: cache
Requires-Dist: cachier; extra == 'cache'
Provides-Extra: cli
Requires-Dist: fire; extra == 'cli'
Requires-Dist: pyyaml; extra == 'cli'
Provides-Extra: spklauto
Requires-Dist: rdflib; extra == 'spklauto'
Requires-Dist: specklepy; extra == 'spklauto'
